continuous_security_account_setup/__init__.py
continuous_security_account_setup/account_bootstrap.py
continuous_security_account_setup/create_org.py
continuous_security_account_setup/org_bootstrap.py
continuous_security_account_setup/organizations.py
continuous_security_account_setup/ou_bootstrap.py
continuous_security_account_setup/sts.py
continuous_security_account_setup-0.0.1.dist-info/LICENSE.md
continuous_security_account_setup-0.0.1.dist-info/METADATA
continuous_security_account_setup-0.0.1.dist-info/WHEEL
continuous_security_account_setup-0.0.1.dist-info/entry_points.txt
continuous_security_account_setup-0.0.1.dist-info/top_level.txt
continuous_security_account_setup-0.0.1.dist-info/RECORD
